pyssem/.DS_Store
pyssem/__init__.py
pyssem/model.py
pyssem/simulation_configurations/opus.json
pyssem/simulation_configurations/opus_test.json
pyssem/source/conf.py
pyssem/source/contents.rst
pyssem/source/index.rst
pyssem/source/model.rst
pyssem/source/tutorial/getting_started.rst
pyssem/utils/.DS_Store
pyssem/utils/__init__.py
pyssem/utils/collisions/NASA_SBM_frags.py
pyssem/utils/collisions/collisions.py
pyssem/utils/drag/__init__.py
pyssem/utils/drag/dens_highvar_2000_dens_highvar_2000_lookup.json
pyssem/utils/drag/drag.py
pyssem/utils/drag/Precomputed/Conversion.ipynb
pyssem/utils/drag/Precomputed/atmospheric_density_data.json
pyssem/utils/drag/Precomputed/dens_highvar_2000.mat
pyssem/utils/drag/Precomputed/dens_highvar_2000_dens_highvar_2000.csv
pyssem/utils/drag/Precomputed/dens_highvar_R02.mat
pyssem/utils/drag/Precomputed/dens_highvar_R02_dens_highvar_R02.csv
pyssem/utils/drag/Precomputed/jb2008_density_profiles.json
pyssem/utils/handlers/datetime_helper.py
pyssem/utils/handlers/handlers.py
pyssem/utils/indicators/LawDF_min_500_fit_range_max_10000_sols_1.csv
"pyssem/utils/indicators/__init__,py"
pyssem/utils/indicators/indicators.py
pyssem/utils/launch/.DS_Store
pyssem/utils/launch/__init__.py
pyssem/utils/launch/launch.py
pyssem/utils/notebooks/UMPY.ipynb
pyssem/utils/notebooks/sep.ipynb
pyssem/utils/plotting/__init__.py
pyssem/utils/plotting/plotting.py
pyssem/utils/pmd/pmd.py
pyssem/utils/simulation/__init__.py
pyssem/utils/simulation/scen_properties.py
pyssem/utils/simulation/species.py
pyssem/utils/simulation/species_pair_class.py
pyssem-0.1.dev294.dist-info/LICENSE.txt
pyssem-0.1.dev294.dist-info/METADATA
pyssem-0.1.dev294.dist-info/WHEEL
pyssem-0.1.dev294.dist-info/top_level.txt
pyssem-0.1.dev294.dist-info/RECORD
