Metadata-Version: 2.1
Name: pyssem
Version: 0.1.dev294
Summary: A source sink model to support the study of the long-term sustainability of Low Earth Orbit (LEO)
Author-email: Indigo Brownhall <indigo.brownhall.20@ucl.ac.uk>
Classifier: Development Status :: 3 - Alpha
Classifier: Intended Audience :: Developers
Classifier: License :: OSI Approved :: MIT License
Classifier: Programming Language :: Python :: 3
Classifier: Programming Language :: Python :: 3.6
Classifier: Programming Language :: Python :: 3.7
Classifier: Programming Language :: Python :: 3.8
Classifier: Programming Language :: Python :: 3.9
Classifier: Programming Language :: Python :: 3.10
License-File: LICENSE.txt
Requires-Dist: setuptools>=68.0.0
Requires-Dist: numpy>=1.2
Requires-Dist: pandas>=2.0
Requires-Dist: scipy>=1.10
Requires-Dist: sympy>=1.11
Requires-Dist: tqdm>=4.65
Requires-Dist: gdown>=4.0.0
Requires-Dist: requests>=2.0
Requires-Dist: bs4
Requires-Dist: matplotlib>=3.0.0
Requires-Dist: loky>=3.0.0
Requires-Dist: imageio>=2.0.0
